adapters/__init__.py
adapters/a2a/aries_adapter.py
adapters/ap2/__init__.py
adapters/ap2/ap2_client.py
adapters/ap2/ap2_mock_server.py
adapters/universal_rail_adapter/__init__.py
adapters/universal_rail_adapter/cardano_adapter.py
adapters/universal_rail_adapter/cardano_midnight_bridge.py
adapters/universal_rail_adapter/eth_adapter.py
adapters/universal_rail_adapter/fabric_adapter.py
adapters/universal_rail_adapter/midnight_adapter.py
api/server.py
cli/__init__.py
cli/cli_main.py
cli/e4a_cli.py
core/__init__.py
core/__version__.py
core/charter_engine.py
core/config_loader.py
core/evolution_engine.py
core/governance_kernel.py
core/mandate_engine.py
core/reputation_index.py
core/scribe_agent.py
core/validator_runtime.py
e4a-1.0.0.dist-info/licenses/LICENSE
e4a_sdk/__init__.py
e4a_sdk/client.py
e4a-1.0.0.dist-info/METADATA
e4a-1.0.0.dist-info/WHEEL
e4a-1.0.0.dist-info/entry_points.txt
e4a-1.0.0.dist-info/top_level.txt
e4a-1.0.0.dist-info/RECORD
