Metadata-Version: 2.4
Name: e4a
Version: 1.0.0
Summary: E4A — Evolutionary Educational Architecture SDK, CLI, and API
Home-page: https://github.com/YOUR_GITHUB_USERNAME/E4A
Author: Dan Everett
Author-email: Dan Everett <deverett@toltoncatholic.org>
License: MIT License
Project-URL: Homepage, https://github.com/YOUR_GITHUB_USERNAME/E4A
Project-URL: Documentation, https://YOUR_GITHUB_USERNAME.github.io/E4A
Project-URL: Repository, https://github.com/YOUR_GITHUB_USERNAME/E4A
Requires-Python: >=3.10
License-File: LICENSE
Requires-Dist: typer>=0.12.3
Requires-Dist: fastapi>=0.111.0
Requires-Dist: uvicorn>=0.30.0
Requires-Dist: requests>=2.31.0
Requires-Dist: pydantic>=2.0
Requires-Dist: httpx>=0.27.0
Dynamic: license-file
